achintya_toolkit/__init__.py
achintya_toolkit/preprocessing.py
achintya_toolkit/test.py
achintya_toolkit-1.0.4.dist-info/METADATA
achintya_toolkit-1.0.4.dist-info/WHEEL
achintya_toolkit-1.0.4.dist-info/top_level.txt
achintya_toolkit-1.0.4.dist-info/RECORD
