Metadata-Version: 2.1
Name: achintya-toolkit
Version: 1.0.4
Summary: This is your one-stop-shop for all the cool and handy code snippets you'll ever need to make ML and DL as easy as pie!
Home-page: https://github.com/Acva11235/achintya-toolkit
Author: Achintya Varshneya
Author-email: achintya.varshneya@gmail.com
License: UNKNOWN
Platform: UNKNOWN
Requires-Dist: opencv-python
